flareradio/__init__.py
flareradio-1.0.2.dist-info/METADATA
flareradio-1.0.2.dist-info/WHEEL
flareradio-1.0.2.dist-info/top_level.txt
flareradio-1.0.2.dist-info/RECORD
